Metadata-Version: 2.1
Name: axonn
Version: 0.2.0
Summary: A parallel library for extreme-scale deep learning
Author-email: Siddharth Singh <ssingh37@umd.edu>, Abhinav Bhatele <bhatele@cs.umd.edu>
License: Apache License
Project-URL: Homepage, https://github.com/axonn-ai/axonn
Project-URL: Issues, https://github.com/axonn-ai/axonn/issues
Project-URL: Docs, https://axonn.readthedocs.io/en/latest/
Classifier: Programming Language :: Python :: 3
Classifier: License :: OSI Approved :: Apache Software License
Classifier: Operating System :: OS Independent
Requires-Python: >=3.8
License-File: LICENSE
Requires-Dist: torch
